base/__init__.py
base/src/__init__.py
base/src/base/__init__.py
base/src/base/app.py
base/src/base/exceptions.py
base/src/base/http.py
base/src/base/orm.py
base/src/base/registry.py
base/src/base/store.py
base/src/base/test.py
base/src/base/token.py
base/src/base/types.py
base/src/base/common/__init__.py
base/src/base/common/utils.py
base/src/base/config/__init__.py
base/src/base/config/config.py
base/src/base/config/config.yaml
base/src/base/helpers/__init__.py
base/src/base/helpers/common.py
base/src/base/helpers/orm_helpers.py
base/src/base/helpers/paginator.py
base/src/base/helpers/tt_paginator.py
base/src/base/lookup/__init__.py
base/src/base/lookup/scope_permissions.py
base/src/base/utils/ipc.py
base/src/base/utils/log.py
base/src/base/utils/sync_order.py
base3-3.4.2.dist-info/LICENSE.txt
base3-3.4.2.dist-info/METADATA
base3-3.4.2.dist-info/WHEEL
base3-3.4.2.dist-info/top_level.txt
base3-3.4.2.dist-info/RECORD
