Metadata-Version: 2.1
Name: base3
Version: 3.4.2
Summary: Base3
Home-page: https://base3.dev
Author: Digital Cube doo
Author-email: info@digitalcube.rs
License: https://www.gnu.org/licenses/gpl-3.0.en.html
Platform: UNKNOWN
Classifier: Intended Audience :: Developers
Classifier: License :: OSI Approved :: GNU General Public License v3 or later (GPLv3+)
Classifier: Natural Language :: English
Classifier: Operating System :: MacOS
Classifier: Operating System :: POSIX
Classifier: Programming Language :: Python :: 3
Classifier: Programming Language :: Python :: 3.8
Classifier: Programming Language :: Python :: 3.9
Classifier: Programming Language :: Python :: Implementation :: CPython
Classifier: Programming Language :: Python :: Implementation :: PyPy
Classifier: Topic :: Software Development
License-File: LICENSE.txt
Requires-Dist: aerich
Requires-Dist: aiomysql
Requires-Dist: aiotask-context
Requires-Dist: asynctest
Requires-Dist: bcrypt
Requires-Dist: logfmt
Requires-Dist: psycopg2-binary
Requires-Dist: PyJWT
Requires-Dist: pyjwt-rsa
Requires-Dist: PyYAML
Requires-Dist: python-dateutil
Requires-Dist: redis
Requires-Dist: requests
Requires-Dist: tornado
Requires-Dist: tortoise-orm[asyncpg]
Requires-Dist: uvloop
Requires-Dist: python-rapidjson
Requires-Dist: ciso8601
